adhan_pi/__init__.py
adhan_pi/cli.py
adhan_pi/config.py
adhan_pi/dataclasses.py
adhan_pi/exceptions.py
adhan_pi/py.typed
adhan_pi/test_mocks.py
adhan_pi/utils.py
adhan_pi/stubs/.flake8
adhan_pi/stubs/crontab.pyi
adhan_pi/stubs/automock/__init__.pyi
adhan_pi/stubs/automock/base.pyi
adhan_pi/stubs/geopy/__init__.pyi
adhan_pi/stubs/geopy/location.pyi
adhan_pi/stubs/geopy/point.pyi
adhan_pi/stubs/geopy/geocoders/__init__.pyi
adhan_pi/stubs/geopy/geocoders/base.pyi
adhan_pi/stubs/geopy/geocoders/nominatim.pyi
adhan_pi/stubs/pydub/__init__.pyi
adhan_pi/stubs/pydub/audio_segment.pyi
adhan_pi/stubs/pydub/playback.pyi
adhan_pi-1.1.0.dist-info/METADATA
adhan_pi-1.1.0.dist-info/WHEEL
adhan_pi-1.1.0.dist-info/entry_points.txt
adhan_pi-1.1.0.dist-info/top_level.txt
adhan_pi-1.1.0.dist-info/RECORD
